autopip/__init__.py
autopip_ninja_22-0.9.dist-info/METADATA
autopip_ninja_22-0.9.dist-info/WHEEL
autopip_ninja_22-0.9.dist-info/top_level.txt
autopip_ninja_22-0.9.dist-info/RECORD
