Metadata-Version: 2.4
Name: autopip-Ninja-22
Version: 0.9
Summary: Python modüllerini otomatik yükleyen kütüphane
Author: Ninja-22
Author-email: sametcevik88@gmail.com
Classifier: Programming Language :: Python :: 3
Classifier: License :: OSI Approved :: MIT License
Classifier: Operating System :: OS Independent
Requires-Python: >=3.6
Requires-Dist: requests>=2.25.1
Dynamic: author
Dynamic: author-email
Dynamic: classifier
Dynamic: description
Dynamic: description-content-type
Dynamic: requires-dist
Dynamic: requires-python
Dynamic: summary
